hooking/__init__.py
hooking/__main__.py
hooking/constant/__init__.py
hooking/context/__init__.py
hooking/dto/__init__.py
hooking/error/__init__.py
hooking/loose/__init__.py
hooking/runner/__init__.py
hooking/tight/__init__.py
tests/__init__.py
tests/test_h.py
tests/util.py
tests/loose/__init__.py
tests/loose/base.py
tests/loose/test.py
tests/tight/__init__.py
tests/tight/base.py
tests/tight/test.py
hooking-0.0.9.dist-info/LICENSE
hooking-0.0.9.dist-info/METADATA
hooking-0.0.9.dist-info/WHEEL
hooking-0.0.9.dist-info/entry_points.txt
hooking-0.0.9.dist-info/top_level.txt
hooking-0.0.9.dist-info/RECORD
