Metadata-Version: 2.1
Name: hooking
Version: 0.0.9
Summary: Generic dual-paradigm hooking mechanism
Home-page: https://github.com/pyrustic/hooking
Author: Pyrustic Evangelist
Author-email: rusticalex@yahoo.com
Maintainer: Pyrustic Evangelist
Maintainer-email: rusticalex@yahoo.com
License: MIT
Keywords: minimalist,generic,hooking,wrap,augment,override,hooks,library,handlers,pyrustic,tag,tagging,events,bind,decorator,decoration,coupling,loose-coupling,tight-coupling,routing,debugging,benchmarking,dual-paradigm,intuitive,api,plugin
Platform: UNKNOWN
Classifier: Programming Language :: Python :: 3
Classifier: License :: OSI Approved :: MIT License
Classifier: Operating System :: OS Independent
Requires-Python: >=3.5
License-File: LICENSE
